MyProjects/Project2/single_sourcecode/single.srcs/sources_1/new/DataMemory.v
`timescale 1ns / 1ps

module DataMemory(clk, address, memread, memwrite, writedata, readdata);
    input clk;
    input [31:0] address;
    input memread, memwrite;
    input [31:0] writedata;
    output reg [31:0] readdata;
    reg [31:0] memory [0:31];
    integer i;
    
    initial begin
        for(i = 0; i < 32; i = i + 1)
            memory[i] = 32'b0;
    end

    always @ (posedge clk) begin
        if (memwrite) begin
             memory[address >> 2] = writedata;
        end
    end

    always @ (*) begin
        if (memread) begin
            readdata = memory[address >> 2];
        end 
        else begin
            readdata = 32'b0;
        end
    end
endmodule

MyProjects/Project2/single_sourcecode/single.srcs/sources_1/new/MUX2_1.v
`timescale 1ns / 1ps

module MUX2_1(in1, in2, out, sel);
    input [31:0] in1, in2;
    input sel;
    output reg [31:0] out;

    always @ (*) begin
        if (sel) begin
            out = in2;
        end
        else begin
            out = in1;
        end
    end
    
endmodule

MyProjects/Project2/single_sourcecode/single.srcs/sources_1/new/ALU.v
`timescale 1ns / 1ps

module ALU(control, in1, in2, zero, result);
    input [3:0] control;
    input [31:0] in1, in2;
    output reg zero;
    output reg [31:0] result;
    initial begin
        result = 32'b0;
    end
    always @ (control or in1 or in2) begin
        case (control)
            4'b0000: result = in1 & in2;
            4'b0001: result = in1 | in2;
            4'b0010: result = in1 + in2;
            4'b0110: result = in1 - in2;
            4'b0111: result = (in1 < in2) ? 1 : 0;
            4'b1100: result = ~(in1 | in2);
        endcase
    end
    always @ (*) begin
        if (result == 0) zero = 1;
        else zero = 0;
    end
endmodule

MyProjects/Project2/single_sourcecode/single.srcs/sources_1/new/ALUcontrol.v
`timescale 1ns / 1ps

module ALUcontrol(ALUop, funcode, control);
    input [1:0] ALUop;
    input [5:0] funcode;
    output reg [3:0] control;

    always @(ALUop or funcode) begin
        case (ALUop)
            2'b00:  control = 4'b0010;
            2'b01: control = 4'b0110;
            2'b10:
                case (funcode) 
                    6'b100000: control = 4'b0010;
                    6'b100010: control = 4'b0110;
                    6'b100100: control = 4'b0000;
                    6'b100101: control = 4'b0001;
                    6'b101010: control = 4'b0111;
                endcase
            2'b11: control = 4'b0000;
        endcase
    end

endmodule

MyProjects/Project2/single_sourcecode/single.srcs/sources_1/new/SignExtend.v
`timescale 1ns / 1ps

module SignExtend(in, out);
    input [15:0] in;
    output [31:0] out;

    assign out[15:0] = in[15:0];
    assign out[31:16] = (in[15]) ? 16'b1111111111111111 : 16'b0;

endmodule

MyProjects/Project2/single_sourcecode/single.srcs/sources_1/new/Register.v
`timescale 1ns / 1ps

module Register(clk, regwrite, readreg1, readreg2, writereg, writedata, readdata1, readdata2);
    input clk, regwrite;
    input [4:0] readreg1, readreg2, writereg;
    input [31:0] writedata;
    output [31:0] readdata1, readdata2;
    reg [31:0] regs [0:31];
    integer i;

    initial begin
        for(i = 0 ; i < 32; i = i + 1) begin
            regs[i] = 32'b0;
        end
    end
	
    always @(posedge clk) begin
        if (regwrite) begin
             regs[writereg] = writedata;
        end
    end
    
    assign readdata1 = regs[readreg1];
    assign readdata2 = regs[readreg2];
    
endmodule

MyProjects/Project2/single_sourcecode/single.srcs/sources_1/new/Control.v
`timescale 1ns / 1ps

module Control(opcode, regdst, jump, beq, bne, memread, memwrite, memtoreg, ALUSrc, regwrite, ALUop);
    input [5:0] opcode;
    output reg regdst, jump, beq, bne, memread, memtoreg, memwrite, ALUSrc, regwrite;
    output reg [1:0] ALUop;

    initial begin
        regdst = 1'b0;
        jump = 1'b0;
        beq = 1'b0;
        bne = 1'b0;
        memread = 1'b0;
        memtoreg = 1'b0;
        memwrite = 1'b0;
        ALUSrc = 1'b0;
        regwrite = 1'b0;
        ALUop = 2'b00;
    end

    always @ (opcode) begin
        case (opcode)
            6'b100011: begin // lw
                regdst = 1'b0;
                jump = 1'b0;
                beq = 1'b0;
                bne = 1'b0;
                memread = 1'b1;
                memtoreg = 1'b1;
                memwrite = 1'b0;
                ALUSrc = 1'b1;
                regwrite = 1'b1;
                ALUop = 2'b00;
            end
            6'b101011: begin // sw
                regdst = 1'b0;
                jump = 1'b0;
                beq = 1'b0;
                bne = 1'b0;
                memread = 1'b0;
                memtoreg = 1'b0;
                memwrite = 1'b1;
                ALUSrc = 1'b1;
                regwrite = 1'b0;
                ALUop = 2'b00;
            end
            6'b000000: begin // add, sub, and, or, slt
                regdst = 1'b1;
                jump = 1'b0;
                beq = 1'b0;
                bne = 1'b0;
                memread = 1'b0;
                memtoreg = 1'b0;
                memwrite = 1'b0;
                ALUSrc = 1'b0;
                regwrite = 1'b1;
                ALUop = 2'b10;
            end
            6'b001000: begin // addi
                regdst = 1'b0;
                jump = 1'b0;
                beq = 1'b0;
                bne = 1'b0;
                memread = 1'b0;
                memtoreg = 1'b0;
                memwrite = 1'b0;
                ALUSrc = 1'b1;
                regwrite = 1'b1;
                ALUop = 2'b00;
            end
            6'b001100: begin // andi
                regdst = 1'b0;
                jump = 1'b0;
                beq = 1'b0;
                bne = 1'b0;
                memread = 1'b0;
                memtoreg = 1'b0;
                memwrite = 1'b0;
                ALUSrc = 1'b1;
                regwrite = 1'b1;
                ALUop = 2'b11;
            end
            6'b000100: begin // beq
                regdst = 1'b1;
                jump = 1'b0;
                beq = 1'b1;
                bne = 1'b0;
                memread = 1'b0;
                memtoreg = 1'b0;
                memwrite = 1'b0;
                ALUSrc = 1'b0;
                regwrite = 1'b0;
                ALUop = 2'b01;
            end
            6'b000101: begin // bne
                regdst = 1'b1;
                jump = 1'b0;
                beq = 1'b0;
                bne = 1'b1;
                memread = 1'b0;
                memtoreg = 1'b0;
                memwrite = 1'b0;
                ALUSrc = 1'b0;
                regwrite = 1'b0;
                ALUop = 2'b01;
            end
            6'b000010: begin // j-type
                regdst = 1'b1;
                jump = 1'b1;
                beq = 1'b0;
                bne = 1'b0;
                memread = 1'b0;
                memtoreg = 1'b0;
                memwrite = 1'b0;
                ALUSrc = 1'b0;
                regwrite = 1'b0;
                ALUop = 2'b00;
            end
        endcase
    end

endmodule

MyProjects/Project2/single_sourcecode/single.srcs/sources_1/new/InstructionMemory.v
`timescale 1ns / 1ps

module InstructionMemory(address, instruction);
    input [31:0] address;
    output [31:0] instruction;
    reg [31:0] memory [0:29];

    initial begin
        memory[0]=32'b00100000000010000000000000100000; //addi $t0, $zero, 0x20
        memory[1]=32'b00100000000010010000000000110111; //addi $t1, $zero, 0x37
        memory[2]=32'b00000001000010011000000000100100; //and $s0, $t0, $t1
        memory[3]=32'b00000001000010011000000000100101; //or $s0, $t0, $t1
        memory[4]=32'b10101100000100000000000000000100; //sw $s0, 4($zero)
        memory[5]=32'b10101100000010000000000000001000; //sw $t0, 8($zero)
        memory[6]=32'b00000001000010011000100000100000; //add $s1, $t0, $t1
        memory[7]=32'b00000001000010011001000000100010; //sub $s2, $t0, $t1
        memory[8]=32'b00010010001100100000000000001001; //beq $s1, $s2, error0
        memory[9]=32'b10001100000100010000000000000100; //lw $s1, 4($zero)
        memory[10]=32'b00110010001100100000000001001000; //andi $s2, $s1, 0x48
        memory[11]=32'b00010010001100100000000000001001; //beq $s1, $s2, error1
        memory[12]=32'b10001100000100110000000000001000; //lw $s3, 8($zero)
        memory[13]=32'b00010010000100110000000000001010; //beq $s0, $s3, error2
        memory[14]=32'b00000010010100011010000000101010; //slt $s4, $s2, $s1 (Last)
        memory[15]=32'b00010010100000000000000000001111; //beq $s4, $0, EXIT
        memory[16]=32'b00000010001000001001000000100000; //add $s2, $s1, $0
        memory[17]=32'b00001000000000000000000000001110; //j Last
        memory[18]=32'b00100000000010000000000000000000; //addi $t0, $0, 0(error0)
        memory[19]=32'b00100000000010010000000000000000; //addi $t1, $0, 0
        memory[20]=32'b00001000000000000000000000011111; //j EXIT
        memory[21]=32'b00100000000010000000000000000001; //addi $t0, $0, 1(error1)
        memory[22]=32'b00100000000010010000000000000001; //addi $t1, $0, 1
        memory[23]=32'b00001000000000000000000000011111; //j EXIT
        memory[24]=32'b00100000000010000000000000000010; //addi $t0, $0, 2(error2)
        memory[25]=32'b00100000000010010000000000000010; //addi $t1, $0, 2
        memory[26]=32'b00001000000000000000000000011111; //j EXIT
        memory[27]=32'b00100000000010000000000000000011; //addi $t0, $0, 3(error3)
        memory[28]=32'b00100000000010010000000000000011; //addi $t1, $0, 3
        memory[29]=32'b00001000000000000000000000011111; //j EXIT
    end

    assign instruction = memory[address >> 2];

endmodule

MyProjects/Project2/single_sourcecode/single.srcs/sources_1/new/PC.v
`timescale 1ns / 1ps

module PC(clk, in, out);
    input clk;   
    input [31:0] in;
    output reg [31:0] out;

    initial begin
        out = 32'b0;
    end

    always @ (posedge clk) begin 
        out = in;
    end    

endmodule

MyProjects/Project2/single_sourcecode/single.srcs/sources_1/new/singlecycle.v
`timescale 1ns / 1ps

module singlecycle(clk);
    input clk;
    wire [31:0] instruction, pcin, pcout, pc4, jumpaddr, branchaddr, tempaddr,
                regreaddata1, regreaddata2, writedata, extend, ALUsec, ALUresult, memreaddata;
    wire [4:0] writereg;
    wire [3:0] ALUcontrol;
    wire [1:0] ALUop;
    wire regwrite, ALUSrc, branch, jump, beq, bne, regdst, memtoreg, memread, memwrite, ALUzero;

    PC pc (
        clk, pcin, pcout
    );

    assign pc4 = pcout + 4;

    InstructionMemory im (
        pcout, instruction
    );

    assign branchaddr = pc4 + (extend << 2);
    assign branch = (ALUzero & beq) | (~ALUzero & bne);
    MUX2_1 temppc(pc4, branchaddr, tempaddr, branch);
    assign jumpaddr = {pc4[31:28], instruction[25:0], 2'b0};
    MUX2_1 finalpc(tempaddr, jumpaddr, pcin, jump);

    Control  control(
        instruction[31:26],
        regdst, jump,
        beq, bne,
        memread, memwrite,
        memtoreg, ALUSrc,
        regwrite, ALUop
    );

    assign writereg = (regdst) ? instruction[15:11] : instruction[20:16];

    Register regs(
        clk, regwrite,
        instruction[25:21], instruction[20:16],
        writereg, writedata,
        regreaddata1, regreaddata2
    );

    SignExtend signextend(
        instruction[15:0], extend
    );

    ALUcontrol alucon(
        ALUop, instruction[5:0], ALUcontrol
    );

    MUX2_1 ALUMUX(regreaddata2, extend, ALUsec, ALUSrc);

    ALU alu(
        ALUcontrol,
        regreaddata1, ALUsec,
        ALUzero, ALUresult
    );

    MUX2_1 daALU(ALUresult, memreaddata, writedata, memtoreg);

    DataMemory dm(
        clk, ALUresult,
        memread, memwrite,
        regreaddata2, memreaddata
    );

endmodule

MyProjects/Project2/single_sourcecode/single.srcs/sim_1/new/test.v
`timescale 1ns / 1ps

module test();
    reg clk;
    integer t;
    singlecycle uut(.clk(clk));

    initial begin
        clk = 0;
        t = 0;
    end

    always #10 begin
        $display("==========================================================");
        $display("Time: %d, CLK = %d, PC = 0x%H", t, clk, uut.pcout);
        $display("[$s0] = 0x%H, [$s1] = 0x%H, [$s2] = 0x%H", uut.regs.regs[16], uut.regs.regs[17], uut.regs.regs[18]);
        $display("[$s3] = 0x%H, [$s4] = 0x%H, [$s5] = 0x%H", uut.regs.regs[19], uut.regs.regs[20], uut.regs.regs[21]);
        $display("[$s6] = 0x%H, [$s7] = 0x%H, [$t0] = 0x%H", uut.regs.regs[22], uut.regs.regs[23], uut.regs.regs[8]);
        $display("[$t1] = 0x%H, [$t2] = 0x%H, [$t3] = 0x%H", uut.regs.regs[9], uut.regs.regs[10], uut.regs.regs[11]);
        $display("[$t4] = 0x%H, [$t5] = 0x%H, [$t6] = 0x%H", uut.regs.regs[12], uut.regs.regs[13], uut.regs.regs[14]);
        $display("[$t7] = 0x%H, [$t8] = 0x%H, [$t9] = 0x%H", uut.regs.regs[15], uut.regs.regs[24], uut.regs.regs[25]);
        clk = ~clk;
        t = t + 10;
    end
    always #1000 $stop;
endmodule

MyProjects/Project2/single_sourcecode/single.sim/sim_1/behav/xsim/singlecycle.vcd
$date
   Sat Nov  7 21:32:46 2020
$end
$version
  2020.1
$end
$timescale
  1ps
$end
$scope module test $end
$scope module uut $end
$var wire 1 ! clk $end
$var wire 32 " instruction [31:0] $end
$var wire 32 # pcin [31:0] $end
$var wire 32 $ pcout [31:0] $end
$var wire 32 % pc4 [31:0] $end
$var wire 32 & jumpaddr [31:0] $end
$var wire 32 ' branchaddr [31:0] $end
$var wire 32 ( tempaddr [31:0] $end
$var wire 32 ) regreaddata1 [31:0] $end
$var wire 32 * regreaddata2 [31:0] $end
$var wire 32 + writedata [31:0] $end
$var wire 32 , extend [31:0] $end
$var wire 32 - ALUsec [31:0] $end
$var wire 32 . ALUresult [31:0] $end
$var wire 32 / memreaddata [31:0] $end
$var wire 5 0 writereg [4:0] $end
$var wire 4 1 ALUcontrol [3:0] $end
$var wire 2 2 ALUop [1:0] $end
$var wire 1 3 regwrite $end
$var wire 1 4 ALUSrc $end
$var wire 1 5 branch $end
$var wire 1 6 jump $end
$var wire 1 7 beq $end
$var wire 1 8 bne $end
$var wire 1 9 regdst $end
$var wire 1 : memtoreg $end
$var wire 1 ; memread $end
$var wire 1 < memwrite $end
$var wire 1 = ALUzero $end
$upscope $end
$upscope $end
$enddefinitions $end
#0
$dumpvars
0!
b100000000010000000000000100000 "
b100 #
b0 $
b100 %
b1000000000000010000000 &
b10000100 '
b100 (
b0 )
b0 *
b100000 +
b100000 ,
b100000 -
b100000 .
b0 /
b1000 0
b10 1
b0 2
13
14
05
06
07
08
09
0:
0;
0<
0=
$end
#10000
1!
b100000000010010000000000110111 "
b1000 #
b100 $
b1000 %
b1001000000000011011100 &
b11100100 '
b1000 (
b0 )
b0 *
b110111 +
b110111 ,
b110111 -
b110111 .
b0 /
b1001 0
0=
#20000
0!
#30000
1!
b1000010011000000000100100 "
b1100 #
b1000 $
b1100 %
b100001001100000000010010000 &
b11111111111111100000000010011100 '
b1100 (
b100000 )
b110111 *
b100000 +
b11111111111111111000000000100100 ,
b110111 -
b100000 .
b0 /
b10000 0
b0 1
b10 2
04
19
0=
#40000
0!
#50000
1!
b1000010011000000000100101 "
b10000 #
b1100 $
b10000 %
b100001001100000000010010100 &
b11111111111111100000000010100100 '
b10000 (
b100000 )
b110111 *
b110111 +
b11111111111111111000000000100101 ,
b110111 -
b110111 .
b0 /
b1 1
0=
#60000
0!
#70000
1!
b10101100000100000000000000000100 "
b10100 #
b10000 $
b10100 %
b10000000000000000010000 &
b100100 '
b10100 (
b0 )
b110111 *
b100 +
b100 ,
b100 -
b100 .
b0 /
b10000 0
b10 1
b0 2
03
14
09
1<
0=
#80000
0!
#90000
1!
b10001100000100010000000000000100 "
b11000 #
b10100 $
b11000 %
b10001000000000000010000 &
b101000 '
b11000 (
b0 *
b110111 +
b100 -
b110111 /
b10001 0
13
1:
1;
0<
#100000
0!
#110000
1!
b1001010000101100000100000 "
b11100 #
b11000 $
b11100 %
b100101000010110000010000000 &
b10110000010011100 '
b11100 (
b110111 )
b100000 *
b1010111 +
b101100000100000 ,
b100000 -
b1010111 .
b0 /
b1011 0
b10 2
04
19
0:
0;
0=
#120000
0!
#130000
1!
b1001010000101100000100010 "
b100000 #
b11100 $
b100000 %
b100101000010110000010001000 &
b10110000010101000 '
b100000 (
b110111 )
b100000 *
b10111 +
b101100000100010 ,
b100000 -
b10111 .
b0 /
b110 1
0=
#140000
0!
#150000
1!
b110001000010110000000000110111 "
b100100 #
b100000 $
b100100 %
b100001011000000000011011100 &
b100000000 '
b100100 (
b100000 )
b10111 *
b100000 +
b110111 ,
b110111 -
b100000 .
b0 /
b1011 0
b0 1
b11 2
14
09
0=
#160000
0!
#170000
1!
b1000010010101100000101010 "
b101000 #
b100100 $
b101000 %
b100001001010110000010101000 &
b10110000011010000 '
b101000 (
b100000 )
b110111 *
b1 +
b101100000101010 ,
b110111 -
b1 .
b0 /
b1011 0
b111 1
b10 2
04
19
0=
#180000
0!
#190000
1!
b10001000010000000000000000001 "
b110000 #
b101000 $
b101100 %
b100001000000000000000000100 &
b110000 '
b110000 (
b100000 )
b100000 *
b0 +
b1 ,
b100000 -
b0 .
b0 /
b0 0
b110 1
b1 2
03
15
17
1=
#200000
0!
#210000
1!
b10101000010010000000000000001 "
b111000 #
b110000 $
b110100 %
b100001001000000000000000100 &
b111000 '
b111000 (
b110111 *
b11111111111111111111111111101001 +
b110111 -
b11111111111111111111111111101001 .
b0 /
b0 0
15
07
18
0=
#220000
0!
#230000
1!
b1000000000000000000000000000 "
b0 #
b111000 $
b111100 %
b0 &
b111100 '
b111100 (
b0 )
b0 *
b0 +
b0 ,
b0 -
b0 .
b0 /
b0 0
b10 2
05
16
08
1=
#240000
0!
#250000
1!
b100000000010000000000000100000 "
b100 #
b0 $
b100 %
b1000000000000010000000 &
b10000100 '
b100 (
b100000 *
b100000 +
b100000 ,
b100000 -
b100000 .
b0 /
b1000 0
b10 1
b0 2
13
14
05
06
09
0=
#260000
0!
#270000
1!
b100000000010010000000000110111 "
b1000 #
b100 $
b1000 %
b1001000000000011011100 &
b11100100 '
b1000 (
b110111 *
b110111 +
b110111 ,
b110111 -
b110111 .
b0 /
b1001 0
0=
